sqlalchemy_django/__init__.py
sqlalchemy_django/middleware.py
sqlalchemy_django/sqlalchemyencoder.py
sqlalchemy_django-0.0.4.dist-info/DESCRIPTION.rst
sqlalchemy_django-0.0.4.dist-info/METADATA
sqlalchemy_django-0.0.4.dist-info/RECORD
sqlalchemy_django-0.0.4.dist-info/WHEEL
sqlalchemy_django-0.0.4.dist-info/metadata.json
sqlalchemy_django-0.0.4.dist-info/top_level.txt
