Metadata-Version: 2.0
Name: sqlalchemy-django
Version: 0.0.4
Summary: similar flask sqlalchemy
Home-page: http://www.hshl.ltd
Author: bigtiger
Author-email: chinafengheping@gmail.com
License: UNKNOWN
Platform: UNKNOWN
Requires-Dist: SQLAlchemy
